linear_algebra_simple/__init__.py
linear_algebra_simple/eigenvector.py
linear_algebra_simple-0.1.0.dist-info/METADATA
linear_algebra_simple-0.1.0.dist-info/WHEEL
linear_algebra_simple-0.1.0.dist-info/top_level.txt
linear_algebra_simple-0.1.0.dist-info/RECORD
